akari_bot_webui/dist/assets/VisibleEditor-C9tD9HPj.js
akari_bot_webui/dist/assets/VisibleEditor-fXM0F31N.css
akari_bot_webui/dist/assets/about-BOqomPgb.css
akari_bot_webui/dist/assets/about-Ok3OM3OM.js
akari_bot_webui/dist/assets/akaribot_logo-DgfyuRg6.png
akari_bot_webui/dist/assets/button-group-Cxdeama3.css
akari_bot_webui/dist/assets/card-D34vavgk.css
akari_bot_webui/dist/assets/card-aXgeqjbf.js
akari_bot_webui/dist/assets/chat-BT1iu-Dz.js
akari_bot_webui/dist/assets/chat-Dm1kT7tX.css
akari_bot_webui/dist/assets/col-C5fj0VQJ.css
akari_bot_webui/dist/assets/col-D2PJq5Mq.js
akari_bot_webui/dist/assets/collapse-item-HUqTMr2R.css
akari_bot_webui/dist/assets/collapse-item-ki0bofbP.js
akari_bot_webui/dist/assets/config-BFdC--7W.css
akari_bot_webui/dist/assets/config-DXIB28mM.js
akari_bot_webui/dist/assets/dashboard-CQjp0mZT.css
akari_bot_webui/dist/assets/dashboard-venezZRR.js
akari_bot_webui/dist/assets/database-Daw4gNJs.js
akari_bot_webui/dist/assets/database-DyDq6oxA.css
akari_bot_webui/dist/assets/empty-iVBaPuAw.css
akari_bot_webui/dist/assets/empty-uWgqmzmm.js
akari_bot_webui/dist/assets/files-BvdD5Y9u.css
akari_bot_webui/dist/assets/files-CtB7zGUc.js
akari_bot_webui/dist/assets/form-item-B4F-CS9A.css
akari_bot_webui/dist/assets/form-item-CPB-nRFs.js
akari_bot_webui/dist/assets/index-Ba1R3pGn.css
akari_bot_webui/dist/assets/index-BhByD-ZT.js
akari_bot_webui/dist/assets/index-CEW755pH.js
akari_bot_webui/dist/assets/index-DOb0_kYk.js
akari_bot_webui/dist/assets/index-DopYfBGO.js
akari_bot_webui/dist/assets/index-YyomBUyK.js
akari_bot_webui/dist/assets/logs-Cu0Wtgpj.css
akari_bot_webui/dist/assets/logs-DDeP8Tz4.js
akari_bot_webui/dist/assets/modules-61fMKUiQ.js
akari_bot_webui/dist/assets/modules-D2CcCFkH.css
akari_bot_webui/dist/assets/pagination-CWQJdt_h.js
akari_bot_webui/dist/assets/pagination-kTVWAHT1.css
akari_bot_webui/dist/assets/popover-CNXEKsvw.css
akari_bot_webui/dist/assets/popover-_FjJ8AfH.js
akari_bot_webui/dist/assets/progress-Br3cjoK6.js
akari_bot_webui-0.3.4.dist-info/METADATA
akari_bot_webui-0.3.4.dist-info/WHEEL
akari_bot_webui-0.3.4.dist-info/licenses/LICENSE
akari_bot_webui-0.3.4.dist-info/RECORD
