Metadata-Version: 2.4
Name: akari-bot-webui
Version: 0.3.4
Summary: 
License-File: LICENSE
Author: OasisAkari
Author-email: oasisakari@gmail.com
Requires-Python: >=3.12
Classifier: Programming Language :: Python :: 3
Classifier: Programming Language :: Python :: 3.12
Classifier: Programming Language :: Python :: 3.13
Classifier: Programming Language :: Python :: 3.14
